{"assets/fonts/Raleway/Raleway-Black.ttf":["assets/fonts/Raleway/Raleway-Black.ttf"],"assets/fonts/Raleway/Raleway-Bold.ttf":["assets/fonts/Raleway/Raleway-Bold.ttf"],"assets/fonts/Raleway/Raleway-Italic.ttf":["assets/fonts/Raleway/Raleway-Italic.ttf"],"assets/fonts/Raleway/Raleway-Light.ttf":["assets/fonts/Raleway/Raleway-Light.ttf"],"assets/fonts/Raleway/Raleway-Regular.ttf":["assets/fonts/Raleway/Raleway-Regular.ttf"],"assets/images/carousel_1.jpg":["assets/images/carousel_1.jpg"],"assets/images/carousel_2.jpg":["assets/images/carousel_2.jpg"],"assets/images/carousel_3.jpg":["assets/images/carousel_3.jpg"],"assets/images/church.jpg":["assets/images/church.jpg"],"assets/images/church_dark.jpg":["assets/images/church_dark.jpg"],"assets/images/ekol.jpeg":["assets/images/ekol.jpeg"],"assets/images/giving.jpg":["assets/images/giving.jpg"],"assets/images/map.png":["assets/images/map.png"],"assets/images/pcg_logo.png":["assets/images/pcg_logo.png"],"assets/images/pcg_main_house.jpeg":["assets/images/pcg_main_house.jpeg"],"assets/images/school.jpg":["assets/images/school.jpg"],"assets/images/school/plan1.jpeg":["assets/images/school/plan1.jpeg"],"assets/images/school/plan2.jpeg":["assets/images/school/plan2.jpeg"],"assets/images/school/plan3.jpeg":["assets/images/school/plan3.jpeg"],"assets/images/school/plan4.jpeg":["assets/images/school/plan4.jpeg"],"assets/images/school/s1.jpeg":["assets/images/school/s1.jpeg"],"assets/images/school/s11.jpeg":["assets/images/school/s11.jpeg"],"assets/images/school/s12.jpeg":["assets/images/school/s12.jpeg"],"assets/images/school/s13.jpeg":["assets/images/school/s13.jpeg"],"assets/images/school/s14.jpeg":["assets/images/school/s14.jpeg"],"assets/images/school/s15.jpeg":["assets/images/school/s15.jpeg"],"assets/images/school/s16.jpeg":["assets/images/school/s16.jpeg"],"assets/images/school/s17.jpeg":["assets/images/school/s17.jpeg"],"assets/images/school/s18.jpeg":["assets/images/school/s18.jpeg"],"assets/images/school/s19.jpeg":["assets/images/school/s19.jpeg"],"assets/images/school/s2.jpeg":["assets/images/school/s2.jpeg"],"assets/images/school/s20.jpeg":["assets/images/school/s20.jpeg"],"assets/images/school/s21.jpeg":["assets/images/school/s21.jpeg"],"assets/images/school/s22.jpeg":["assets/images/school/s22.jpeg"],"assets/images/school/s23.jpeg":["assets/images/school/s23.jpeg"],"assets/images/school/s24.jpeg":["assets/images/school/s24.jpeg"],"assets/images/school/s25.jpeg":["assets/images/school/s25.jpeg"],"assets/images/school/s26.jpeg":["assets/images/school/s26.jpeg"],"assets/images/school/s27.jpeg":["assets/images/school/s27.jpeg"],"assets/images/school/s28.jpeg":["assets/images/school/s28.jpeg"],"assets/images/school/s3.jpeg":["assets/images/school/s3.jpeg"],"assets/images/school/s4.jpeg":["assets/images/school/s4.jpeg"],"assets/images/school/s5.jpeg":["assets/images/school/s5.jpeg"],"assets/images/school/s6.jpeg":["assets/images/school/s6.jpeg"],"assets/images/school/s7.jpeg":["assets/images/school/s7.jpeg"],"assets/images/school/s8.jpeg":["assets/images/school/s8.jpeg"],"assets/images/school/s9.jpeg":["assets/images/school/s9.jpeg"],"assets/images/social_icons/facebook.png":["assets/images/social_icons/facebook.png"],"assets/images/social_icons/instagram.png":["assets/images/social_icons/instagram.png"],"assets/images/social_icons/linkedin.png":["assets/images/social_icons/linkedin.png"],"assets/images/social_icons/twitter.png":["assets/images/social_icons/twitter.png"],"assets/images/social_icons/whatsapp.png":["assets/images/social_icons/whatsapp.png"],"assets/images/social_icons/youtube.png":["assets/images/social_icons/youtube.png"],"assets/images/toilet/t1.jpeg":["assets/images/toilet/t1.jpeg"],"assets/images/toilet/t10.jpeg":["assets/images/toilet/t10.jpeg"],"assets/images/toilet/t2.jpeg":["assets/images/toilet/t2.jpeg"],"assets/images/toilet/t3.jpeg":["assets/images/toilet/t3.jpeg"],"assets/images/toilet/t4.jpeg":["assets/images/toilet/t4.jpeg"],"assets/images/toilet/t5.jpeg":["assets/images/toilet/t5.jpeg"],"assets/images/toilet/t6.jpeg":["assets/images/toilet/t6.jpeg"],"assets/images/toilet/t7.jpeg":["assets/images/toilet/t7.jpeg"],"assets/images/toilet/t8.jpeg":["assets/images/toilet/t8.jpeg"],"assets/images/toilet/t9.jpeg":["assets/images/toilet/t9.jpeg"],"assets/images/washroom.jpg":["assets/images/washroom.jpg"],"packages/cupertino_icons/assets/CupertinoIcons.ttf":["packages/cupertino_icons/assets/CupertinoIcons.ttf"],"packages/flutter_inappwebview/t_rex_runner/t-rex.css":["packages/flutter_inappwebview/t_rex_runner/t-rex.css"],"packages/flutter_inappwebview/t_rex_runner/t-rex.html":["packages/flutter_inappwebview/t_rex_runner/t-rex.html"]}